odoo/addons/account_cutoff_accrual_sale_stock/README.rst
odoo/addons/account_cutoff_accrual_sale_stock/__init__.py
odoo/addons/account_cutoff_accrual_sale_stock/__manifest__.py
odoo/addons/account_cutoff_accrual_sale_stock/i18n/account_cutoff_accrual_sale_stock.pot
odoo/addons/account_cutoff_accrual_sale_stock/i18n/it.po
odoo/addons/account_cutoff_accrual_sale_stock/models/__init__.py
odoo/addons/account_cutoff_accrual_sale_stock/models/sale_order_line.py
odoo/addons/account_cutoff_accrual_sale_stock/readme/CONTRIBUTORS.rst
odoo/addons/account_cutoff_accrual_sale_stock/readme/DESCRIPTION.rst
odoo/addons/account_cutoff_accrual_sale_stock/static/description/icon.png
odoo/addons/account_cutoff_accrual_sale_stock/static/description/index.html
odoo/addons/account_cutoff_accrual_sale_stock/tests/__init__.py
odoo/addons/account_cutoff_accrual_sale_stock/tests/common.py
odoo/addons/account_cutoff_accrual_sale_stock/tests/test_cutoff_revenue.py
odoo/addons/account_cutoff_accrual_sale_stock/tests/test_cutoff_revenue_on_delivery.py
odoo/addons/account_cutoff_accrual_sale_stock/tests/test_cutoff_revenue_on_order.py
odoo_addon_account_cutoff_accrual_sale_stock-16.0.1.1.0.dist-info/METADATA
odoo_addon_account_cutoff_accrual_sale_stock-16.0.1.1.0.dist-info/WHEEL
odoo_addon_account_cutoff_accrual_sale_stock-16.0.1.1.0.dist-info/top_level.txt
odoo_addon_account_cutoff_accrual_sale_stock-16.0.1.1.0.dist-info/RECORD
